{
    "code": 10000,
    "msg": "请求处理成功",
    "length": "100",
    "data": [
        {
            "name": "吕晓创",
            "status": "待审核",
            "time": "2016-04-22 12:36:58",
            "color": 2
        },
       {
            "name": "吕晓创",
            "status": "待审核",
            "time": "2016-04-22 12:36:58",
            "color": 1
        },
        {
            "name": "吕晓创",
            "status": "待审核",
            "time": "2016-04-22 12:36:58",
            "color": 2
        },
       {
            "name": "吕晓创",
            "status": "待审核",
            "time": "2016-04-22 12:36:58",
            "color": 1
        }
    ]
}